django_chart_component/__init__.py
django_chart_component/static/index-bundle.js
django_chart_component-0.1.0.dist-info/METADATA
django_chart_component-0.1.0.dist-info/WHEEL
django_chart_component-0.1.0.dist-info/top_level.txt
django_chart_component-0.1.0.dist-info/RECORD
