Metadata-Version: 2.2
Name: django-chart-component
Version: 0.1.0
Summary: Chartjs support for Django
Author-email: Paul Traylor <kungfudiscomonkey@gmail.com>
Requires-Python: >=3.8
